cuborg/__init__.py
cuborg-0.0.1.dist-info/LICENSE
cuborg-0.0.1.dist-info/METADATA
cuborg-0.0.1.dist-info/WHEEL
cuborg-0.0.1.dist-info/top_level.txt
cuborg-0.0.1.dist-info/RECORD
